{"note":"Don't delete this file! It's used internally to help with page regeneration.","body":"# c\r\n\r\nGive folders or directories comments and view them easy.\r\n\r\nOriginal idea by [Jonovono](https://github.com/Jonovono/c)\r\n\r\n## Installation\r\nInstall the module with: `npm install c -g`\r\n\r\n## Examples\r\n\r\nRun it without any parameter to see the usage\r\n\r\n    help:\r\n    help:   c - Add comments to any file or directory.\r\n    help:\r\n    help:   Usage:\r\n    help:\r\n    help:        c list   [DIRECTORY]                 - Lists all the comments for the [DIRECTORY].\r\n    help:        c add    [FILE|DIRECTORY] [COMMENT]  - Adds a comment for the file/directory.\r\n    help:        c set    [FILE|DIRECTORY] [COMMENT]  - Sets a new comment for the file/directory.\r\n    help:        c delete [FILE|DIRECTORY]            - Deletes all the comments for the file/directory.\r\n    help:\r\n    help:   Author: Djordje Lukic <lukic.djordje@gmail.com>\r\n    help:   Stolen from Jonovono (https://github.com/Jonovono/c)\r\n\r\n\r\nList the comments\r\n\r\n    $ c l .\r\n\r\n    Comments for this directory:\r\n\r\n      .npmignore\r\n      bin\r\n\r\nAdd a comment to a folder/file\r\n\r\n    $ c add bin This is the bin folder\r\n    $ c list .\r\n\r\n    Comments for this directory:\r\n\r\n      .npmignore\r\n      bin               This is the bin folder\r\n\r\nRemove comments from a folder/file\r\n\r\n    $ c rm bin\r\n    $ c l .\r\n\r\n    Comments for this directory:\r\n\r\n      .npmignore\r\n      bin\r\n\r\n## TODO\r\n\r\nTests tests tests\r\n\r\n## License\r\n\r\nMIT: http://rumpl.mit-license.org\r\n","name":"C","tagline":"Add comments on any file or folder.","google":""}